MANIFEST.in
README.md
setup.py
sepiida/__init__.py
sepiida/backend.py
sepiida/callback.py
sepiida/context.py
sepiida/cors.py
sepiida/endpoints.py
sepiida/environment.py
sepiida/errors.py
sepiida/fields.py
sepiida/fixtures.py
sepiida/groups.py
sepiida/jwt.py
sepiida/log.py
sepiida/memberships.py
sepiida/options.py
sepiida/parsing.py
sepiida/permissions.py
sepiida/prometheus.py
sepiida/requests.py
sepiida/responses.py
sepiida/routing.py
sepiida/sentry.py
sepiida/serialization.py
sepiida/session.py
sepiida/storage.py
sepiida/testing.py
sepiida/wsgi.py
sepiida/zipbuf.py
sepiida.egg-info/PKG-INFO
sepiida.egg-info/SOURCES.txt
sepiida.egg-info/dependency_links.txt
sepiida.egg-info/entry_points.txt
sepiida.egg-info/requires.txt
sepiida.egg-info/top_level.txt