Metadata-Version: 1.0
Name: sepiida
Version: 18.8
Summary: The root library, bringer of common code and goodness
Home-page: https://bitbucket.org/Authentise/sepiida.git
Author: Authentise, Inc.
Author-email: engineering@authentise.com
License: UNKNOWN
Platform: UNKNOWN
